limits_exporter/__init__.py
limits_exporter-0.1.0.data/scripts/limits_exporter
limits_exporter-0.1.0.dist-info/LICENSE
limits_exporter-0.1.0.dist-info/METADATA
limits_exporter-0.1.0.dist-info/WHEEL
limits_exporter-0.1.0.dist-info/top_level.txt
limits_exporter-0.1.0.dist-info/RECORD
