Metadata-Version: 2.1
Name: limits-exporter
Version: 0.1.0
Summary: prometheus exporter for openstack compute limits in projects
Home-page: https://github.com/cloudcentric/limits_exporter
Author: Felix Ehrenpfort
Author-email: felix.ehrenpfort@codecentric.cloud
License: MIT
Platform: UNKNOWN
Requires-Dist: openstacksdk
Requires-Dist: prometheus-client
